jira_amt/__init__.py
jira_amt/__main__.py
jira_amt/cli.py
jira_amt/config.py
jira_amt/jira.py
jira_amt-1.3.1.dist-info/LICENSE
jira_amt-1.3.1.dist-info/METADATA
jira_amt-1.3.1.dist-info/WHEEL
jira_amt-1.3.1.dist-info/entry_points.txt
jira_amt-1.3.1.dist-info/RECORD
