Metadata-Version: 2.1
Name: jira-amt
Version: 1.3.1
Summary: Manage Jira assets.
Home-page: https://arash-hatami.ir
License: MIT
Keywords: jira,asset
Author: Arash Hatami
Author-email: hatamiarash7@gmail.com
Requires-Python: >=3.8,<4.0
Classifier: Development Status :: 5 - Production/Stable
Classifier: License :: OSI Approved :: MIT License
Classifier: Programming Language :: Python :: 3
Classifier: Programming Language :: Python :: 3.8
Classifier: Programming Language :: Python :: 3.9
Classifier: Programming Language :: Python :: 3.10
Classifier: Programming Language :: Python :: 3.11
Classifier: Topic :: Software Development
Classifier: Topic :: Software Development :: Libraries
Requires-Dist: requests (>=2,<3)
Requires-Dist: tomlkit (>=0.12.0,<0.13.0)
Requires-Dist: typer[all] (>=0.9.0,<0.10.0)
Requires-Dist: urllib3 (>=1,<2)
Project-URL: Bug Tracker, https://github.com/hatamiarash7/jira-asset-manager/issues
Project-URL: Repository, https://github.com/hatamiarash7/jira-asset-manager
